graphql_complexity/__init__.py
graphql_complexity/config.py
graphql_complexity/estimators/__init__.py
graphql_complexity/estimators/base.py
graphql_complexity/estimators/directive.py
graphql_complexity/estimators/simple.py
graphql_complexity/evaluator/__init__.py
graphql_complexity/evaluator/complexity.py
graphql_complexity/evaluator/nodes.py
graphql_complexity/evaluator/utils.py
graphql_complexity/evaluator/visitor.py
graphql_complexity/extensions/__init__.py
graphql_complexity/extensions/strawberry_graphql.py
graphql_complexity-0.3.2.dist-info/LICENSE
graphql_complexity-0.3.2.dist-info/METADATA
graphql_complexity-0.3.2.dist-info/WHEEL
graphql_complexity-0.3.2.dist-info/RECORD
