Metadata-Version: 2.1
Name: graphql_complexity
Version: 0.3.2
Summary: A python library that provides complexity calculation helpers for GraphQL
Home-page: https://github.com/Checho3388/graphql-complexity
License: MIT
Keywords: graphql,complexity,query,mutation,subscription
Author: Checho3388
Author-email: ezequiel.grondona@gmail.com
Requires-Python: >=3.10,<4.0
Classifier: Development Status :: 4 - Beta
Classifier: Intended Audience :: Developers
Classifier: License :: OSI Approved :: MIT License
Classifier: Programming Language :: Python :: 3
Classifier: Programming Language :: Python :: 3.10
Classifier: Programming Language :: Python :: 3.11
Classifier: Programming Language :: Python :: 3.12
Classifier: Topic :: Software Development :: Libraries :: Python Modules
Provides-Extra: strawberry-graphql
Requires-Dist: graphql-core (>=3.2.3,<4.0.0)
Requires-Dist: strawberry-graphql (>=0.219.2,<0.220.0) ; extra == "strawberry-graphql"
Project-URL: Repository, https://github.com/Checho3388/graphql-complexity
